pyminiply/reader.py
pyminiply/_wrapper.pyi
pyminiply/__init__.py
pyminiply/py.typed
pyminiply/_wrapper.abi3.so
pyminiply-0.2.3.dist-info/WHEEL
pyminiply-0.2.3.dist-info/METADATA
pyminiply-0.2.3.dist-info/RECORD
pyminiply-0.2.3.dist-info/licenses/LICENSE
