Metadata-Version: 2.1
Name: pyminiply
Version: 0.2.3
Summary: Rapidly read in PLY files using a wrapper over miniply
Author-Email: PyVista Developers <info@pyvista.org>
Classifier: License :: OSI Approved :: MIT License
Classifier: Operating System :: Microsoft :: Windows
Classifier: Operating System :: POSIX
Classifier: Intended Audience :: Science/Research
Classifier: Programming Language :: Python :: 3.9
Classifier: Programming Language :: Python :: 3.10
Classifier: Programming Language :: Python :: 3.11
Classifier: Programming Language :: Python :: 3.12
Classifier: Programming Language :: Python :: 3.13
Requires-Python: >=3.9
Requires-Dist: numpy
Provides-Extra: pyvista
Requires-Dist: pyvista; extra == "pyvista"
